thad_roberts_model/__init__.py
thad_roberts_model/measurement.py
thad_roberts_model/particles_masses.py
thad_roberts_model/thad_roberts_model.py
thad_roberts_model-0.1.6.1.dist-info/LICENSE
thad_roberts_model-0.1.6.1.dist-info/METADATA
thad_roberts_model-0.1.6.1.dist-info/WHEEL
thad_roberts_model-0.1.6.1.dist-info/top_level.txt
thad_roberts_model-0.1.6.1.dist-info/RECORD
