Metadata-Version: 2.1
Name: thad-roberts-model
Version: 0.1.6.1
Summary: Thad Roberts Model Library
Home-page: https://github.com/lukaszp/thad-roberts-model.git
Author: Lukasz Paszke
Author-email: lukasz.paszke@gmail.com
License: MIT
Platform: UNKNOWN
Classifier: Programming Language :: Python :: 3
Classifier: License :: OSI Approved :: MIT License
Classifier: Operating System :: OS Independent
Requires-Python: >=3.7
Provides-Extra: dev
Requires-Dist: twine ; extra == 'dev'
